line_detector.cpython-36m-darwin.so
line_detector-0.1.7.dist-info/DESCRIPTION.rst
line_detector-0.1.7.dist-info/METADATA
line_detector-0.1.7.dist-info/RECORD
line_detector-0.1.7.dist-info/WHEEL
line_detector-0.1.7.dist-info/metadata.json
line_detector-0.1.7.dist-info/top_level.txt
