Metadata-Version: 2.0
Name: line-detector
Version: 0.1.7
Summary: My short description for my project.
Home-page: UNKNOWN
Author: Lucien Liu
Author-email: lucien_rd@163.com
License: GNU GPLv3
Platform: linux
Classifier: License :: OSI Approved :: GNU General Public License v3 (GPLv3)
Classifier: Programming Language :: Python :: 3
Classifier: Programming Language :: Python :: 3.6
Classifier: Programming Language :: Python :: Implementation :: CPython
Requires-Python: >=3.6.0
Requires-Dist: numpy
